setup.py
contextchecker/__init__.py
contextchecker/check_context.py
contextchecker/contextualize.py
contextchecker/dot_product_attention.py
contextchecker/embeddings_generator.py
contextchecker/imports.py
contextchecker/text_preprocessor.py
contextchecker/visualizer.py
contextchecker.egg-info/PKG-INFO
contextchecker.egg-info/SOURCES.txt
contextchecker.egg-info/dependency_links.txt
contextchecker.egg-info/top_level.txt