Metadata-Version: 2.1
Name: contextchecker
Version: 0.0.4
Summary: A Python Package for checking possibility of certain words to appear in similar context
Author: Zephania Reuben
Author-email: zreuben815@gmail.com
License: MIT
